wgfrontend/__init__.py
wgfrontend/config.py
wgfrontend/exechelper.py
wgfrontend/pwdtools.py
wgfrontend/setupenv.py
wgfrontend/setupenv_alpine.py
wgfrontend/test_cherrypy.py
wgfrontend/webapp.py
wgfrontend/wgcfg.py
wgfrontend/templates/base.html
wgfrontend/templates/config.html
wgfrontend/templates/edit.html
wgfrontend/templates/index.html
wgfrontend/templates/login.html
wgfrontend/templates/part_header.html
wgfrontend/webroot/static/favicon.ico
wgfrontend/webroot/static/logo.svg
wgfrontend/webroot/static/styles.css
wgfrontend-1.0.1.dist-info/LICENSE
wgfrontend-1.0.1.dist-info/METADATA
wgfrontend-1.0.1.dist-info/WHEEL
wgfrontend-1.0.1.dist-info/entry_points.txt
wgfrontend-1.0.1.dist-info/top_level.txt
wgfrontend-1.0.1.dist-info/RECORD
