Metadata-Version: 2.1
Name: wgfrontend
Version: 1.0.1
Summary: web-based user interface for configuring WireGuard for roadwarriors
Home-page: https://www.github.com/towalink/wgfrontend
Author: The Towalink Project
Author-email: pypi.wgfrontend@towalink.net
Project-URL: Project homepage, https://www.towalink.net
Project-URL: Repository, https://www.github.com/towalink/wgfrontend
Project-URL: Documentation, https://towalink.readthedocs.io
Keywords: Towalink VPN WireGuard frontend gui
Classifier: Programming Language :: Python
Classifier: Programming Language :: Python :: 3
Classifier: License :: OSI Approved :: GNU Affero General Public License v3 or later (AGPLv3+)
Classifier: Operating System :: POSIX :: Linux
Classifier: Development Status :: 5 - Production/Stable
Classifier: Intended Audience :: System Administrators
Classifier: Intended Audience :: Information Technology
Classifier: Intended Audience :: Telecommunications Industry
Classifier: Topic :: System :: Networking
Requires-Python: >=3.6
License-File: LICENSE
Requires-Dist: cherrypy
Requires-Dist: jinja2
Requires-Dist: qrcode[pil]
Requires-Dist: wgconfig
